template_fragments/__init__.py
template_fragments/_base.py
template_fragments/jinja.py
template_fragments-23.6.0.dist-info/METADATA
template_fragments-23.6.0.dist-info/WHEEL
template_fragments-23.6.0.dist-info/top_level.txt
template_fragments-23.6.0.dist-info/RECORD
