Metadata-Version: 2.1
Name: template-fragments
Version: 23.6.0
Summary: Template fragments for jinja-like engines
Author-email: Christopher Prohm <mail@cprohm.de>
License: MIT
Project-URL: Repository, https://github.com/chmp/template-fragments-py
Requires-Python: >=3.8
Provides-Extra: dev
Requires-Dist: build ; extra == 'dev'
Requires-Dist: black ; extra == 'dev'
Requires-Dist: ruff ; extra == 'dev'
Requires-Dist: jinja2 ; extra == 'dev'
Requires-Dist: pytest ; extra == 'dev'
Requires-Dist: flask ; extra == 'dev'
Provides-Extra: jinja
Requires-Dist: jinja2 ; extra == 'jinja'
